{"__type__":"dragonBones.DragonBonesAsset","_name":"af_ske","_dragonBonesJson":"{\"frameRate\":24,\"isGlobal\":0,\"name\":\"af\",\"version\":\"4.5\",\"armature\":[{\"slot\":[{\"displayIndex\":5,\"name\":\"sheetSlot\",\"parent\":\"root\",\"color\":{}}],\"skin\":[{\"name\":\"\",\"slot\":[{\"display\":[{\"path\":\"Image 1\",\"type\":\"image\",\"name\":\"Image 1\",\"transform\":{\"y\":-54}},{\"path\":\"Image 2\",\"type\":\"image\",\"name\":\"Image 2\",\"transform\":{\"y\":-54}},{\"path\":\"Image 3\",\"type\":\"image\",\"name\":\"Image 3\",\"transform\":{\"y\":-54}},{\"path\":\"Image 4\",\"type\":\"image\",\"name\":\"Image 4\",\"transform\":{\"y\":-54}},{\"path\":\"Image 5\",\"type\":\"image\",\"name\":\"Image 5\",\"transform\":{\"y\":-54}},{\"path\":\"Image 6\",\"type\":\"image\",\"name\":\"Image 6\",\"transform\":{\"y\":-54}}],\"name\":\"sheetSlot\"}]}],\"animation\":[{\"frame\":[],\"duration\":6,\"bone\":[],\"ik\":[],\"slot\":[{\"frame\":[{\"tweenEasing\":null,\"duration\":1},{\"tweenEasing\":null,\"displayIndex\":1,\"duration\":1},{\"tweenEasing\":null,\"displayIndex\":2,\"duration\":1},{\"tweenEasing\":null,\"displayIndex\":3,\"duration\":1},{\"tweenEasing\":null,\"displayIndex\":4,\"duration\":1},{\"tweenEasing\":null,\"displayIndex\":5,\"duration\":1}],\"name\":\"sheetSlot\"}],\"ffd\":[],\"name\":\"run\",\"playTimes\":0}],\"type\":\"Sheet\",\"frameRate\":12,\"ik\":[],\"aabb\":{\"width\":67,\"y\":-107.5,\"height\":107,\"x\":-33.5},\"defaultActions\":[{\"gotoAndPlay\":\"run\"}],\"name\":\"run\",\"bone\":[{\"name\":\"root\",\"transform\":{}}]},{\"slot\":[{\"displayIndex\":4,\"name\":\"sheetSlot\",\"parent\":\"root\",\"color\":{}}],\"skin\":[{\"name\":\"\",\"slot\":[{\"display\":[{\"path\":\"Image 7\",\"type\":\"image\",\"name\":\"Image 7\",\"transform\":{\"y\":-56.25}},{\"path\":\"Image 8\",\"type\":\"image\",\"name\":\"Image 8\",\"transform\":{\"y\":-56.25,\"x\":-1}},{\"path\":\"Image 9\",\"type\":\"image\",\"name\":\"Image 9\",\"transform\":{\"y\":-56.25,\"x\":-1}},{\"path\":\"Image 10\",\"type\":\"image\",\"name\":\"Image 10\",\"transform\":{\"y\":-56.25,\"x\":-1}},{\"path\":\"Image 11\",\"type\":\"image\",\"name\":\"Image 11\",\"transform\":{\"y\":-56.25,\"x\":-1}},{\"path\":\"Image 12\",\"type\":\"image\",\"name\":\"Image 12\",\"transform\":{\"y\":-56.25,\"x\":-1}}],\"name\":\"sheetSlot\"}]}],\"animation\":[{\"frame\":[],\"duration\":6,\"bone\":[],\"ik\":[],\"slot\":[{\"frame\":[{\"tweenEasing\":null,\"duration\":1},{\"tweenEasing\":null,\"displayIndex\":1,\"duration\":1},{\"tweenEasing\":null,\"displayIndex\":2,\"duration\":1},{\"tweenEasing\":null,\"displayIndex\":3,\"duration\":1},{\"tweenEasing\":null,\"displayIndex\":4,\"duration\":1},{\"tweenEasing\":null,\"displayIndex\":5,\"duration\":1}],\"name\":\"sheetSlot\"}],\"ffd\":[],\"name\":\"idle\",\"playTimes\":0}],\"type\":\"Sheet\",\"frameRate\":12,\"ik\":[],\"aabb\":{\"width\":55,\"y\":-113.25,\"height\":114,\"x\":-28.5},\"defaultActions\":[{\"gotoAndPlay\":\"idle\"}],\"name\":\"idle\",\"bone\":[{\"name\":\"root\",\"transform\":{}}]},{\"slot\":[{\"displayIndex\":1,\"name\":\"sheetSlot\",\"parent\":\"root\",\"color\":{}}],\"skin\":[{\"name\":\"\",\"slot\":[{\"display\":[{\"path\":\"Image 18\",\"type\":\"image\",\"name\":\"Image 18\",\"transform\":{\"y\":-57}},{\"path\":\"Image 17\",\"type\":\"image\",\"name\":\"Image 17\",\"transform\":{\"y\":-57}},{\"path\":\"Image 16\",\"type\":\"image\",\"name\":\"Image 16\",\"transform\":{\"y\":-56,\"x\":1}},{\"path\":\"Image 15\",\"type\":\"image\",\"name\":\"Image 15\",\"transform\":{\"y\":-53,\"x\":19}},{\"path\":\"Image 14\",\"type\":\"image\",\"name\":\"Image 14\",\"transform\":{\"y\":-52,\"x\":18}},{\"path\":\"Image 13\",\"type\":\"image\",\"name\":\"Image 13\",\"transform\":{\"y\":-57,\"x\":13}}],\"name\":\"sheetSlot\"}]}],\"animation\":[{\"frame\":[],\"duration\":6,\"bone\":[],\"ik\":[],\"slot\":[{\"frame\":[{\"tweenEasing\":null,\"duration\":1},{\"tweenEasing\":null,\"displayIndex\":1,\"duration\":1},{\"tweenEasing\":null,\"displayIndex\":2,\"duration\":1},{\"tweenEasing\":null,\"displayIndex\":3,\"duration\":1},{\"tweenEasing\":null,\"displayIndex\":4,\"duration\":1},{\"tweenEasing\":null,\"displayIndex\":5,\"duration\":1}],\"name\":\"sheetSlot\"}],\"ffd\":[],\"name\":\"release\",\"playTimes\":0}],\"type\":\"Sheet\",\"frameRate\":12,\"ik\":[],\"aabb\":{\"width\":69,\"y\":-112.5,\"height\":111,\"x\":-34.5},\"defaultActions\":[{\"gotoAndPlay\":\"release\"}],\"canvas\":{\"width\":94,\"y\":-54,\"height\":119,\"x\":9},\"name\":\"release\",\"bone\":[{\"name\":\"root\",\"transform\":{}}]},{\"slot\":[{\"name\":\"sheetSlot\",\"parent\":\"root\",\"color\":{}}],\"skin\":[{\"name\":\"\",\"slot\":[{\"display\":[{\"path\":\"Image 24\",\"type\":\"image\",\"name\":\"Image 24\",\"transform\":{\"y\":-57}},{\"path\":\"Image 22\",\"type\":\"image\",\"name\":\"Image 22\",\"transform\":{\"y\":-55,\"x\":-1}},{\"path\":\"Image 21\",\"type\":\"image\",\"name\":\"Image 21\",\"transform\":{\"y\":-55,\"x\":5}},{\"path\":\"Image 20\",\"type\":\"image\",\"name\":\"Image 20\",\"transform\":{\"y\":-55,\"x\":27}},{\"path\":\"Image 19\",\"type\":\"image\",\"name\":\"Image 19\",\"transform\":{\"y\":-56,\"x\":14}}],\"name\":\"sheetSlot\"}]}],\"animation\":[{\"frame\":[],\"duration\":5,\"bone\":[],\"ik\":[],\"slot\":[{\"frame\":[{\"tweenEasing\":null,\"duration\":1},{\"tweenEasing\":null,\"displayIndex\":1,\"duration\":1},{\"tweenEasing\":null,\"displayIndex\":2,\"duration\":1},{\"tweenEasing\":null,\"displayIndex\":3,\"duration\":1},{\"tweenEasing\":null,\"displayIndex\":4,\"duration\":1}],\"name\":\"sheetSlot\"}],\"ffd\":[],\"name\":\"attack\",\"playTimes\":0}],\"type\":\"Sheet\",\"frameRate\":12,\"ik\":[],\"aabb\":{\"width\":59,\"y\":-113.5,\"height\":113,\"x\":-29.5},\"defaultActions\":[{\"gotoAndPlay\":\"attack\"}],\"name\":\"attack\",\"bone\":[{\"name\":\"root\",\"transform\":{}}]},{\"slot\":[{\"displayIndex\":4,\"name\":\"sheetSlot\",\"parent\":\"root\",\"color\":{}}],\"skin\":[{\"name\":\"\",\"slot\":[{\"display\":[{\"path\":\"Image 48\",\"type\":\"image\",\"name\":\"Image 48\",\"transform\":{\"y\":-56}},{\"path\":\"Image 47\",\"type\":\"image\",\"name\":\"Image 47\",\"transform\":{\"y\":-54,\"x\":2}},{\"path\":\"Image 46\",\"type\":\"image\",\"name\":\"Image 46\",\"transform\":{\"y\":-54,\"x\":3}},{\"path\":\"Image 45\",\"type\":\"image\",\"name\":\"Image 45\",\"transform\":{\"y\":-43,\"x\":38}},{\"path\":\"Image 44\",\"type\":\"image\",\"name\":\"Image 44\",\"transform\":{\"y\":-35,\"x\":44}}],\"name\":\"sheetSlot\"}]}],\"animation\":[{\"frame\":[],\"duration\":5,\"bone\":[],\"ik\":[],\"slot\":[{\"frame\":[{\"tweenEasing\":null,\"duration\":1},{\"tweenEasing\":null,\"displayIndex\":1,\"duration\":1},{\"tweenEasing\":null,\"displayIndex\":2,\"duration\":1},{\"tweenEasing\":null,\"displayIndex\":3,\"duration\":1},{\"tweenEasing\":null,\"displayIndex\":4,\"duration\":1}],\"name\":\"sheetSlot\"}],\"ffd\":[],\"name\":\"died\"}],\"type\":\"Sheet\",\"frameRate\":12,\"ik\":[],\"aabb\":{\"width\":108,\"y\":-72,\"height\":74,\"x\":-10},\"defaultActions\":[{\"gotoAndPlay\":\"died\"}],\"name\":\"died\",\"bone\":[{\"name\":\"root\",\"transform\":{}}]},{\"slot\":[{\"name\":\"sheetSlot\",\"parent\":\"root\",\"color\":{}}],\"skin\":[{\"name\":\"\",\"slot\":[{\"display\":[{\"path\":\"Image 41\",\"type\":\"image\",\"name\":\"Image 41\",\"transform\":{\"y\":-61}}],\"name\":\"sheetSlot\"}]}],\"animation\":[{\"frame\":[],\"duration\":1,\"bone\":[],\"ik\":[],\"slot\":[{\"frame\":[{\"tweenEasing\":null,\"duration\":1}],\"name\":\"sheetSlot\"}],\"ffd\":[],\"name\":\"jump\"}],\"type\":\"Sheet\",\"frameRate\":12,\"ik\":[],\"aabb\":{\"width\":68,\"y\":-122,\"height\":122,\"x\":-34},\"defaultActions\":[{\"gotoAndPlay\":\"jump\"}],\"name\":\"jump\",\"bone\":[{\"name\":\"root\",\"transform\":{}}]},{\"slot\":[{\"name\":\"sheetSlot\",\"parent\":\"root\",\"color\":{}}],\"skin\":[{\"name\":\"\",\"slot\":[{\"display\":[{\"path\":\"Image 42\",\"type\":\"image\",\"name\":\"Image 42\",\"transform\":{}}],\"name\":\"sheetSlot\"}]}],\"animation\":[{\"frame\":[],\"duration\":1,\"bone\":[],\"ik\":[],\"slot\":[{\"frame\":[{\"tweenEasing\":null,\"duration\":1}],\"name\":\"sheetSlot\"}],\"ffd\":[],\"name\":\"head\"}],\"type\":\"Sheet\",\"frameRate\":12,\"ik\":[],\"aabb\":{\"width\":74,\"y\":-36.5,\"height\":73,\"x\":-37},\"defaultActions\":[{\"gotoAndPlay\":\"head\"}],\"name\":\"head\",\"bone\":[{\"name\":\"root\",\"transform\":{}}]}]}"}